__pyinstaller/__init__.py
__pyinstaller/hook-caver.py
__pyinstaller/hook-pre_edited_cs.py
caver/__init__.py
caver/patcher.py
caver/py.typed
caver/tsc_file.lua
caver/version.py
pre_edited_cs/Config.dat
pre_edited_cs/DoConfig.exe
pre_edited_cs/Doukutsu.exe
pre_edited_cs/__init__.py
pre_edited_cs/dinput.dll
pre_edited_cs/data/Arms.bmp
pre_edited_cs/data/ArmsImage.bmp
pre_edited_cs/data/ArmsItem.tsc
pre_edited_cs/data/Bullet.bmp
pre_edited_cs/data/Caret.bmp
pre_edited_cs/data/Credit.tsc
pre_edited_cs/data/Face.bmp
pre_edited_cs/data/Fade.bmp
pre_edited_cs/data/Head.tsc
pre_edited_cs/data/ItemImage.bmp
pre_edited_cs/data/Loading.bmp
pre_edited_cs/data/MyChar.bmp
pre_edited_cs/data/StageImage.bmp
pre_edited_cs/data/StageSelect.tsc
pre_edited_cs/data/TextBox.bmp
pre_edited_cs/data/Title.bmp
pre_edited_cs/data/bk0.bmp
pre_edited_cs/data/bkBlack.bmp
pre_edited_cs/data/bkBlue.bmp
pre_edited_cs/data/bkFall.bmp
pre_edited_cs/data/bkFog.bmp
pre_edited_cs/data/bkGard.bmp
pre_edited_cs/data/bkGray.bmp
pre_edited_cs/data/bkGreen.bmp
pre_edited_cs/data/bkMaze.bmp
pre_edited_cs/data/bkMoon.bmp
pre_edited_cs/data/bkRed.bmp
pre_edited_cs/data/bkWater.bmp
pre_edited_cs/data/casts.bmp
pre_edited_cs/data/mrmap.bin
pre_edited_cs/data/npc.tbl
pre_edited_cs/data/stageconv.exe
pre_edited_cs/data/tsc_def.txt
pre_edited_cs/data/uuid.txt
pre_edited_cs/data/Font/LICENSE-dejavu.txt
pre_edited_cs/data/Font/font
pre_edited_cs/data/Npc/Npc0.bmp
pre_edited_cs/data/Npc/NpcAlmo1.bmp
pre_edited_cs/data/Npc/NpcAlmo2.bmp
pre_edited_cs/data/Npc/NpcBallos.bmp
pre_edited_cs/data/Npc/NpcBllg.bmp
pre_edited_cs/data/Npc/NpcCemet.bmp
pre_edited_cs/data/Npc/NpcCent.bmp
pre_edited_cs/data/Npc/NpcCurly.bmp
pre_edited_cs/data/Npc/NpcDark.bmp
pre_edited_cs/data/Npc/NpcDr.bmp
pre_edited_cs/data/Npc/NpcEggs1.bmp
pre_edited_cs/data/Npc/NpcEggs2.bmp
pre_edited_cs/data/Npc/NpcFrog.bmp
pre_edited_cs/data/Npc/NpcGuest.bmp
pre_edited_cs/data/Npc/NpcHell.bmp
pre_edited_cs/data/Npc/NpcHeri.bmp
cave_story_randomizer-2.2.2.dist-info/LICENSE
cave_story_randomizer-2.2.2.dist-info/METADATA
cave_story_randomizer-2.2.2.dist-info/WHEEL
cave_story_randomizer-2.2.2.dist-info/entry_points.txt
cave_story_randomizer-2.2.2.dist-info/top_level.txt
cave_story_randomizer-2.2.2.dist-info/RECORD
