Metadata-Version: 2.1
Name: cave-story-randomizer
Version: 2.2.2
Summary: An open source randomizer patcher for Cave Story.
Home-page: https://github.com/cave-story-randomizer/cave-story-randomizer/tree/patcher
Author: duncathan salt
Classifier: License :: OSI Approved :: zlib/libpng License
Classifier: Development Status :: 5 - Production/Stable
Classifier: Intended Audience :: Developers
Classifier: Programming Language :: Python :: 3.9
Classifier: Programming Language :: Other Scripting Engines
Requires-Python: >=3.9
License-File: LICENSE
Requires-Dist: lupa >=1.10
